bigmcl/__init__.py
bigmcl/bigmcl.py
bigmcl-0.2b2.data/scripts/bigmcl.py
bigmcl-0.2b2.dist-info/LICENSE
bigmcl-0.2b2.dist-info/METADATA
bigmcl-0.2b2.dist-info/WHEEL
bigmcl-0.2b2.dist-info/top_level.txt
bigmcl-0.2b2.dist-info/RECORD
