Metadata-Version: 2.1
Name: bigmcl
Version: 0.2b2
Summary: Large scale Markov clustering (MCL) via subgraph extraction
Home-page: https://gitlab.com/xonq/bigmcl
Author: xonq
Author-email: konkelzach@protonmail.com
Classifier: Programming Language :: Python :: 3
Classifier: License :: OSI Approved :: BSD License
Classifier: Operating System :: POSIX :: Linux
Requires-Python: >=3.0,<4
License-File: LICENSE
